Metadata-Version: 2.1
Name: mailify
Version: 2.0.7
Summary: Simple library to write python emails
Home-page: https://github.com/samrath-est/mailer.git
Author: EncoreSky Technologies
Author-email: samrathpatidar@encoresky.com
License: MIT
Platform: UNKNOWN
